pyphony/__init__.py
pyphony/alphabet.py
pyphony/conversion.py
pyphony/lexicon.py
pyphony/parser/__init__.py
pyphony/parser/wiktionary.py
pyphony/resources/__init__.py
pyphony/resources/alphabets/ipa.json
pyphony/resources/alphabets/marytts_de.json
pyphony/resources/alphabets/sampa.json
pyphony/resources/alphabets/xsampa.json
pyphony/resources/conversion/ipa_to_marytts_de.json
pyphony/resources/conversion/ipa_to_xsampa.json
pyphony/resources/conversion/marytts_de_to_ipa.json
pyphony-0.1.0.dist-info/LICENSE
pyphony-0.1.0.dist-info/METADATA
pyphony-0.1.0.dist-info/WHEEL
pyphony-0.1.0.dist-info/top_level.txt
pyphony-0.1.0.dist-info/RECORD
