Metadata-Version: 2.1
Name: pyphony
Version: 0.1.0
Summary: pyphony is a library to handle lexica for ASR.
Home-page: https://github.com/ynop/pyphony
Author: Matthias Buechi
Author-email: buec@zhaw.ch
License: MIT
Download-URL: https://github.com/ynop/pyphony/releases
Keywords: speech recognition lexicon dictionary phone phoneme pronunciation
Platform: UNKNOWN
Classifier: Intended Audience :: Science/Research
Classifier: License :: OSI Approved :: MIT License
Classifier: Programming Language :: Python :: 3 :: Only
Classifier: Topic :: Scientific/Engineering :: Human Machine Interfaces
Requires-Dist: tqdm (==4.39.0)
Provides-Extra: ci
Requires-Dist: flake8 (==3.7.9) ; extra == 'ci'
Requires-Dist: flake8-quotes (==2.1.1) ; extra == 'ci'
Provides-Extra: dev
Requires-Dist: click (==7.0) ; extra == 'dev'
Requires-Dist: pytest (==5.2.3) ; extra == 'dev'
Requires-Dist: pytest-runner (==5.2) ; extra == 'dev'
Requires-Dist: pytest-cov (==2.8.1) ; extra == 'dev'
Requires-Dist: pytest-benchmark (==3.2.2) ; extra == 'dev'
